CHANGELOG.md
najia/__init__.py
najia/__main__.py
najia/const.py
najia/data/guaci.pkl
najia/data/standard.tpl
najia/najia.py
najia/utils.py
najia-2.0.1.dist-info/LICENSE
najia-2.0.1.dist-info/METADATA
najia-2.0.1.dist-info/WHEEL
najia-2.0.1.dist-info/entry_points.txt
najia-2.0.1.dist-info/RECORD
