Metadata-Version: 2.1
Name: najia
Version: 2.0.1
Summary: 
Home-page: https://github.com/bopo/najia
License: MIT
Author: bopo
Author-email: ibopo@126.com
Requires-Python: >=3.9,<4.0
Classifier: License :: OSI Approved :: MIT License
Classifier: Programming Language :: Python :: 3
Classifier: Programming Language :: Python :: 3.9
Classifier: Programming Language :: Python :: 3.10
Classifier: Programming Language :: Python :: 3.11
Requires-Dist: arrow (>=1.2.3,<2.0.0)
Requires-Dist: click (>=8.1.3,<9.0.0)
Requires-Dist: jinja2 (>=3.1.2,<4.0.0)
Requires-Dist: lunar-python (>=1.3.2,<2.0.0)
Project-URL: Repository, https://github.com/bopo/najia
